README.rst
setup.cfg
setup.py
vdm/__init__.py
vdm.egg-info/PKG-INFO
vdm.egg-info/SOURCES.txt
vdm.egg-info/dependency_links.txt
vdm.egg-info/not-zip-safe
vdm.egg-info/top_level.txt
vdm/sqlalchemy/__init__.py
vdm/sqlalchemy/base.py
vdm/sqlalchemy/demo.py
vdm/sqlalchemy/demo_meta.py
vdm/sqlalchemy/demo_simple.py
vdm/sqlalchemy/sqla.py
vdm/sqlalchemy/stateful.py
vdm/sqlalchemy/test_demo.py
vdm/sqlalchemy/test_demo_misc.py
vdm/sqlalchemy/test_stateful.py
vdm/sqlalchemy/test_stateful_collections.py
vdm/sqlalchemy/test_tools.py
vdm/sqlalchemy/tools.py