Metadata-Version: 1.1
Name: vdm
Version: 0.15
Summary: A versioned domain model framework.
Home-page: http://www.okfn.org/vdm/
Author: Rufus Pollock (Open Knowledge Foundation)
Author-email: info@okfn.org
License: MIT
Download-URL: https://github.com/okfn/vdm
Keywords: versioning sqlobject sqlalchemy orm
Platform: UNKNOWN
Classifier: Development Status :: 4 - Beta
Classifier: Environment :: Console
Classifier: Intended Audience :: Developers
Classifier: License :: OSI Approved :: MIT License
Classifier: Operating System :: OS Independent
Classifier: Programming Language :: Python
Classifier: Topic :: Software Development :: Libraries :: Python Modules
